mystai/__init__.py
mystai-0.0.1.dist-info/LICENSE
mystai-0.0.1.dist-info/METADATA
mystai-0.0.1.dist-info/WHEEL
mystai-0.0.1.dist-info/top_level.txt
mystai-0.0.1.dist-info/RECORD
